GenJianyuXueGoFix1/README.md
GenJianyuXueGoFix1/__init__.py
GenJianyuXueGoFix1/__main__.py
GenJianyuXueGoFix1/file.epub
GenJianyuXueGoFix1/index.html
GenJianyuXueGoFix1/css/__init__.py
GenJianyuXueGoFix1/css/annotations.css
GenJianyuXueGoFix1/css/main.css
GenJianyuXueGoFix1/css/normalize.css
GenJianyuXueGoFix1/css/popup.css
GenJianyuXueGoFix1/font/__init__.py
GenJianyuXueGoFix1/font/fontello.eot
GenJianyuXueGoFix1/font/fontello.svg
GenJianyuXueGoFix1/font/fontello.ttf
GenJianyuXueGoFix1/font/fontello.woff
GenJianyuXueGoFix1/img/__init__.py
GenJianyuXueGoFix1/img/annotator-glyph-sprite.png
GenJianyuXueGoFix1/img/annotator-icon-sprite.png
GenJianyuXueGoFix1/img/apple-touch-icon.png
GenJianyuXueGoFix1/img/cancelfullscreen.png
GenJianyuXueGoFix1/img/close.png
GenJianyuXueGoFix1/img/fullscreen.png
GenJianyuXueGoFix1/img/loader.gif
GenJianyuXueGoFix1/img/menu-icon.png
GenJianyuXueGoFix1/img/save.png
GenJianyuXueGoFix1/img/saved.png
GenJianyuXueGoFix1/img/settings-s.png
GenJianyuXueGoFix1/img/settings.png
GenJianyuXueGoFix1/img/star.png
GenJianyuXueGoFix1/js/__init__.py
GenJianyuXueGoFix1/js/epub.js
GenJianyuXueGoFix1/js/epub.min.js
GenJianyuXueGoFix1/js/epub.min.map
GenJianyuXueGoFix1/js/hooks.min.js
GenJianyuXueGoFix1/js/hooks.min.map
GenJianyuXueGoFix1/js/reader.js
GenJianyuXueGoFix1/js/reader.js.map
GenJianyuXueGoFix1/js/reader.min.js
GenJianyuXueGoFix1/js/reader.min.map
GenJianyuXueGoFix1/js/hooks/__init__.py
GenJianyuXueGoFix1/js/hooks/extensions/__init__.py
GenJianyuXueGoFix1/js/hooks/extensions/highlight.js
GenJianyuXueGoFix1/js/libs/__init__.py
GenJianyuXueGoFix1/js/libs/jquery.min.js
GenJianyuXueGoFix1/js/libs/localforage.min.js
GenJianyuXueGoFix1/js/libs/screenfull.js
GenJianyuXueGoFix1/js/libs/screenfull.min.js
GenJianyuXueGoFix1/js/libs/zip.min.js
GenJianyuXueGoFix1/js/plugins/__init__.py
GenJianyuXueGoFix1/js/plugins/hypothesis.js
GenJianyuXueGoFix1/js/plugins/search.js
gen_jianyu_xue_go_fix1-2025.3.25.0.dist-info/METADATA
gen_jianyu_xue_go_fix1-2025.3.25.0.dist-info/WHEEL
gen_jianyu_xue_go_fix1-2025.3.25.0.dist-info/entry_points.txt
gen_jianyu_xue_go_fix1-2025.3.25.0.dist-info/top_level.txt
gen_jianyu_xue_go_fix1-2025.3.25.0.dist-info/RECORD
